{"type":"Sprite","props":{"zOrder":10,"y":0,"x":0,"width":120,"texture":"other/green.png","scaleY":0.7,"scaleX":0.7,"presetID":1,"name":"GreenBrick","isPresetRoot":true,"height":80},"compId":1701,"child":[{"type":"Script","props":{"y":0,"x":0,"width":120,"presetID":2,"height":80,"friction":0,"runtime":"laya.physics.BoxCollider"},"compId":271},{"type":"Script","props":{"type":"static","presetID":3,"mask":62,"category":1,"runtime":"laya.physics.RigidBody"},"compId":272}],"loadList":["other/green.png"],"loadList3D":[]}