{"type":"Sprite","props":{"zOrder":10,"y":0,"texture":"other/rewardFrame.png","scaleY":0.7,"scaleX":0.7,"presetID":1,"name":"PassLevelBrick","isPresetRoot":true},"compId":1584,"child":[{"type":"Script","props":{"width":166,"presetID":2,"label":"PassLevelBrick","isSensor":true,"height":166,"runtime":"laya.physics.BoxCollider"},"compId":1585},{"type":"Script","props":{"type":"static","presetID":3,"mask":58,"category":4,"runtime":"laya.physics.RigidBody"},"compId":1586},{"type":"Animation","props":{"y":98,"x":83,"width":1,"source":"anim/PassEffect.ani","scaleY":1.5,"scaleX":1.5,"presetID":4,"pivotY":34,"name":"render","height":1,"autoPlay":true,"autoAnimation":"ani1"},"compId":1588},{"type":"Script","props":{"presetID":5,"runtime":"script/PassLevelBrickLogic.js"},"compId":1589},{"type":"Animation","props":{"y":-156,"x":-353,"width":100,"source":"anim/YanHua1.ani","rotation":107,"presetID":7,"name":"yanhua1","height":100,"autoPlay":true},"compId":1593},{"type":"Animation","props":{"y":-406,"x":-205,"width":100,"source":"anim/YanHua2.ani","presetID":8,"name":"yanhua2","height":100,"autoPlay":true},"compId":1594},{"type":"Animation","props":{"y":-178,"x":135,"width":100,"source":"anim/YanHua3.ani","presetID":9,"name":"yanhua3","height":100,"autoPlay":true},"compId":1595},{"type":"Animation","props":{"y":-318,"x":267,"width":100,"source":"anim/YanHua4.ani","presetID":10,"name":"yanhua4","height":100,"autoPlay":true},"compId":1596},{"type":"Animation","props":{"y":-168,"x":570,"width":100,"source":"anim/YanHua5.ani","presetID":11,"name":"yanhua5","height":100,"autoPlay":true},"compId":1597},{"type":"Animation","props":{"y":-256,"x":-36,"width":100,"source":"anim/YanHua6.ani","presetID":12,"name":"yanhua6","height":100,"autoPlay":true},"compId":1598}],"loadList":["other/rewardFrame.png","anim/PassEffect.ani","anim/YanHua1.ani","anim/YanHua2.ani","anim/YanHua3.ani","anim/YanHua4.ani","anim/YanHua5.ani","anim/YanHua6.ani"],"loadList3D":[]}